[
  {
    "title": "HobbyHub",
    "description": "A local hobby group organizer with member management and event scheduling.",
    "image": "https://i.ibb.co/8gsXBcm6/hobby-hub-web.webp",
    "tech": ["React", "Node.js", "MongoDB"],
    "live": "https://hobbyhub.example.com",
    "github": "https://hobby-hub-papaya.web.app/"
  },
  {
    "title": "Hotel Booking App",
    "description": "A dynamic hotel booking system with real-time availability and user reviews.",
    "image": "https://i.ibb.co/5X1mBw7n/sunsetbay-website.webp",
    "tech": ["React", "Node.js", "MongoDB", "Firebase"],
    "live": "https://sunsetbay-hotel.netlify.app/",
    "github": "https://github.com/jakariya0dev/hotel-booking-client"
  },
  {
    "title": "POS System",
    "description": "An inventory and invoice management system for small shopkeepers with Bluetooth printer integration.",
    "image": "https://i.ibb.co/SXRGBJ3d/mobile-pos.webp",
    "tech": ["Flutter", "Firebase"],
    "live": "https://youtu.be/pTmSQlxBnp4?si=ulLLLGxNxHQttaJ2",
    "github": "https://github.com/jakariya0dev/cafe21"
  }
]
